hydraml/__init__.py
hydraml-0.0.1.dist-info/LICENSE
hydraml-0.0.1.dist-info/METADATA
hydraml-0.0.1.dist-info/WHEEL
hydraml-0.0.1.dist-info/top_level.txt
hydraml-0.0.1.dist-info/RECORD
